{
  "author": "BAYJID",
  "autoRestart": true,
  "accpetPending": false,
  "developermode": false,
  "language": "en",
  "notification": false,
  "approval": false,
  "saveState": false,
  "BOTNAME": "BAYJID-CAT_6T9",
  "PREFIX": "/",
  "OPERATOR": [
    "100065506668822"
  ],
  "ADMINBOT": [
    "100065506668822",
    ""
  ],
  "OWNER": ["100065506668822"], 
  "APPROVED": [],
  "disabledcmds": [],
  "disabledevents": [],
  "note": "make sure that the bot name you entered is all lowercase",
  "notice": "dont cng author name and owner uid. otherwise bot not working",
  "notice2": "if you run use email and password, use saveState false; otherwise, use saveState true"
}
